pyrestcli/__init__.py
pyrestcli/auth.py
pyrestcli/exceptions.py
pyrestcli/fields.py
pyrestcli/paginators.py
pyrestcli/resources.py
pyrestcli-0.6.12.dist-info/AUTHORS.md
pyrestcli-0.6.12.dist-info/LICENSE
pyrestcli-0.6.12.dist-info/METADATA
pyrestcli-0.6.12.dist-info/WHEEL
pyrestcli-0.6.12.dist-info/top_level.txt
pyrestcli-0.6.12.dist-info/RECORD
